setup.py
geosearch_py/__init__.py
geosearch_py/geo_search.py
geosearch_py.egg-info/PKG-INFO
geosearch_py.egg-info/SOURCES.txt
geosearch_py.egg-info/dependency_links.txt
geosearch_py.egg-info/not-zip-safe
geosearch_py.egg-info/pbr.json
geosearch_py.egg-info/top_level.txt