Metadata-Version: 1.0
Name: geosearch-py
Version: 0.1
Summary: A Python implementation of Gmaps geocode API, capable or returning viewport and geometric bounds
Home-page: https://github.com/csunsong/geosearch_py
Author: Chris Sunsong
Author-email: csunsong@gmail.com
License: MIT
Platform: UNKNOWN
